KenengShiRangNiShouyifeiqianDeYingyuJinjieZhinan/README.md
KenengShiRangNiShouyifeiqianDeYingyuJinjieZhinan/__init__.py
KenengShiRangNiShouyifeiqianDeYingyuJinjieZhinan/__main__.py
KenengShiRangNiShouyifeiqianDeYingyuJinjieZhinan/file.epub
KenengShiRangNiShouyifeiqianDeYingyuJinjieZhinan/index.html
KenengShiRangNiShouyifeiqianDeYingyuJinjieZhinan/css/__init__.py
KenengShiRangNiShouyifeiqianDeYingyuJinjieZhinan/css/annotations.css
KenengShiRangNiShouyifeiqianDeYingyuJinjieZhinan/css/main.css
KenengShiRangNiShouyifeiqianDeYingyuJinjieZhinan/css/normalize.css
KenengShiRangNiShouyifeiqianDeYingyuJinjieZhinan/css/popup.css
KenengShiRangNiShouyifeiqianDeYingyuJinjieZhinan/font/__init__.py
KenengShiRangNiShouyifeiqianDeYingyuJinjieZhinan/font/fontello.eot
KenengShiRangNiShouyifeiqianDeYingyuJinjieZhinan/font/fontello.svg
KenengShiRangNiShouyifeiqianDeYingyuJinjieZhinan/font/fontello.ttf
KenengShiRangNiShouyifeiqianDeYingyuJinjieZhinan/font/fontello.woff
KenengShiRangNiShouyifeiqianDeYingyuJinjieZhinan/img/__init__.py
KenengShiRangNiShouyifeiqianDeYingyuJinjieZhinan/img/annotator-glyph-sprite.png
KenengShiRangNiShouyifeiqianDeYingyuJinjieZhinan/img/annotator-icon-sprite.png
KenengShiRangNiShouyifeiqianDeYingyuJinjieZhinan/img/apple-touch-icon.png
KenengShiRangNiShouyifeiqianDeYingyuJinjieZhinan/img/cancelfullscreen.png
KenengShiRangNiShouyifeiqianDeYingyuJinjieZhinan/img/close.png
KenengShiRangNiShouyifeiqianDeYingyuJinjieZhinan/img/fullscreen.png
KenengShiRangNiShouyifeiqianDeYingyuJinjieZhinan/img/loader.gif
KenengShiRangNiShouyifeiqianDeYingyuJinjieZhinan/img/menu-icon.png
KenengShiRangNiShouyifeiqianDeYingyuJinjieZhinan/img/save.png
KenengShiRangNiShouyifeiqianDeYingyuJinjieZhinan/img/saved.png
KenengShiRangNiShouyifeiqianDeYingyuJinjieZhinan/img/settings-s.png
KenengShiRangNiShouyifeiqianDeYingyuJinjieZhinan/img/settings.png
KenengShiRangNiShouyifeiqianDeYingyuJinjieZhinan/img/star.png
KenengShiRangNiShouyifeiqianDeYingyuJinjieZhinan/js/__init__.py
keneng_shi_rang_ni_shouyifeiqian_de_yingyu_jinjie_zhinan-2024.3.5.0.dist-info/METADATA
keneng_shi_rang_ni_shouyifeiqian_de_yingyu_jinjie_zhinan-2024.3.5.0.dist-info/WHEEL
keneng_shi_rang_ni_shouyifeiqian_de_yingyu_jinjie_zhinan-2024.3.5.0.dist-info/entry_points.txt
keneng_shi_rang_ni_shouyifeiqian_de_yingyu_jinjie_zhinan-2024.3.5.0.dist-info/top_level.txt
keneng_shi_rang_ni_shouyifeiqian_de_yingyu_jinjie_zhinan-2024.3.5.0.dist-info/RECORD
